{
  "project_info": {
    "project_number": "1033251430272",
    "project_id": "pictures-com-pk",
    "storage_bucket": "pictures-com-pk.appspot.com"
  },
  "client": [
    {
      "client_info": {
        "mobilesdk_app_id": "1:1033251430272:android:8522f6bf209ebf3bf7ab65",
        "android_client_info": {
          "package_name": "com.example.pictures_dot_com"
        }
      },
      "oauth_client": [],
      "api_key": [
        {
          "current_key": "AIzaSyD7OY6sX6uK61KslFsFTwD3Oj0RlRiw-kE"
        }
      ],
      "services": {
        "appinvite_service": {
          "other_platform_oauth_client": []
        }
      }
    }
  ],
  "configuration_version": "1"
}